SWANi/__init__.py
SWANi/__main__.py
SWANi/strings.py
SWANi/SWANiSlicer/SWANiSlicer.py
SWANi/SWANiSlicer/__init__.py
SWANi/SWANiSlicer/slicerScript.py
SWANi/SWANiWorkflow/SWANiLib.py
SWANi/SWANiWorkflow/__init__.py
SWANi/SWANiWorkflow/mainWorkflow.py
SWANi/SWANiWorkflow/workflowThread.py
SWANi/UI/__init__.py
SWANi/UI/customTreeWidgetItem.py
SWANi/UI/mainWindow.py
SWANi/UI/persistentProgressDialog.py
SWANi/UI/preferencesWindow.py
SWANi/UI/ptTAB.py
SWANi/UI/verticalScrollArea.py
SWANi/utils/APPLABELS.py
SWANi/utils/SWANiConfig.py
SWANi/utils/__init__.py
SWANi/utils/check_dependency.py
SWANi/utils/dicomSearch.py
SWANi/utils/modulecheck.py
SWANi-0.1.18.dist-info/LICENSE
SWANi-0.1.18.dist-info/METADATA
SWANi-0.1.18.dist-info/WHEEL
SWANi-0.1.18.dist-info/entry_points.txt
SWANi-0.1.18.dist-info/top_level.txt
SWANi-0.1.18.dist-info/RECORD
